[
  {
    "iconUrl": "https://raw.githubusercontent.com/lodistream/lodistream.github.io/refs/heads/master/logo.png",
    "apiVersion": 1,
    "repositoryUrl": "https://github.com/GitLatte/Sinetech",
    "fileSize": 19020,
    "status": 1,
    "language": "de",
    "authors": [
      "lodistream"
    ],
    "tvTypes": [
      "AnimeMovie",
      "Anime",
      "OVA"
    ],
    "version": 4,
    "internalName": "Aniworld MC - lodistream",
    "description": "açıklama kısmı",
    "url": "https://raw.githubusercontent.com/GitLatte/Sinetech/builds/Aniworld MC - LoDi.cs3",
    "name": "lodistream"
  },
  {
    "iconUrl": "https://raw.githubusercontent.com/lodistream/lodistream.github.io/refs/heads/master/logo.png",
    "apiVersion": 1,
    "repositoryUrl": "https://github.com/GitLatte/Sinetech",
    "fileSize": 23749,
    "status": 1,
    "language": "tr",
    "authors": [
      "lodistream",
    ],
    "tvTypes": [
      "TvSeries"
    ],
    "version": 4,
    "internalName": "Ddizi-lodi",
    "description": "Ddizi, dizi izle, dizi seyret, ddizi.im - Güncel ve eski dizileri en iyi görüntü kalitesiyle bulabileceğiniz dizi izleme sitesi.",
    "url": "https://raw.githubusercontent.com/GitLatte/Sinetech/builds/DDizi - LoDi.cs3",
    "name": "lodistream"
  },
  {
    "iconUrl": "https://raw.githubusercontent.com/lodistream/lodistream.github.io/refs/heads/master/logo.png",
    "apiVersion": 1,
    "repositoryUrl": "https://github.com/GitLatte/Sinetech",
    "fileSize": 24355,
    "status": 1,
    "language": "tr",
    "authors": [
      "lodistream"
    ],
    "tvTypes": [
      "TvSeries",
      "Movie"
    ],
    "version": 5,
    "internalName": "DiziFun- lodi ",
    "description": "Dizifun, yabancı dizi - film, yerli dizi - film , türkçe dublaj , türkçe altyazılı ve anime dizi - film izlemeniz için sizinledir.",
    "url": "https://raw.githubusercontent.com/GitLatte/Sinetech/builds/DiziFun - LoDi.cs3",
    "name": "DiziFun - LoDi"
  },
  {
    "iconUrl": "https://raw.githubusercontent.com/GitLatte/temporarylists/refs/heads/main/img/gofilm.png",
    "apiVersion": 1,
    "repositoryUrl": "https://github.com/GitLatte/Sinetech",
    "fileSize": 27666,
    "status": 1,
    "language": "tr",
    "authors": [
      "lodistream"
    ],
    "tvTypes": [
      "Movie"
    ],
    "version": 3,
    "internalName": "GoFilmIzle - lodi",
    "description": "GoFilmizle | Yerli ve Yabancı Full HD Film izleme Sitesi - Diziler çalışmaz.",
    "url": "https://raw.githubusercontent.com/GitLatte/Sinetech/builds/GoFilmIzle - LoDi.cs3",
    "name": "GoFilmIzle - LoDi"
  },
  {
    "iconUrl": "https://raw.githubusercontent.com/lodistream/lodistream.github.io/refs/heads/master/logo.png",
    "apiVersion": 1,
    "repositoryUrl": "https://github.com/GitLatte/Sinetech",
    "fileSize": 26613,
    "status": 1,
    "language": "tr",
    "authors": [
      "lodistream"
    ],
    "tvTypes": [
      "TvSeries",
      "Movie"
    ],
    "version": 3,
    "internalName": "KICK Türkiye ",
    "description": "Kick'teki Türkçe canlı yayınlar ve popüler yayıncıları canlı izleyin. Arayın, bulun  ve izlemeye devam edin.",
    "url": "https://raw.githubusercontent.com/GitLatte/Sinetech/builds/KICK Türkiye - LoDi.cs3",
    "name": "KICK Türkiye - LoDi"
  },
  {
    "iconUrl": "https://raw.githubusercontent.com/lodistream/lodistream.github.io/refs/heads/master/logo.png",
    "apiVersion": 1,
    "repositoryUrl": "https://github.com/GitLatte/Sinetech",
    "fileSize": 19932,
    "status": 1,
    "language": "tr",
    "authors": [
      "lodistream"
    ],
    "tvTypes": [
      "Live"
    ],
    "version": 3,
    "internalName": "myway TV ",
    "description": "Sinetech.tr Forum myway canlı tv listesi",
    "url": "https://raw.githubusercontent.com/GitLatte/Sinetech/builds/myway TV - LoDi.cs3",
    "name": "myway TV - LoDi"
  },
  {
    "iconUrl": "https://raw.githubusercontent.com/GitLatte/temporarylists/refs/heads/main/img/muzikkanallari.png",
    "apiVersion": 1,
    "repositoryUrl": "https://github.com/GitLatte/Sinetech",
    "fileSize": 23377,
    "status": 1,
    "language": "tr",
    "authors": [
      "lodistream"
    ],
    "tvTypes": [
      "Live"
    ],
    "version": 3,
    "internalName": "Müzik TV ve Radyo - LoDi",
    "description": "Müzik Kanallarına özel canlı tv eklentisidir.",
    "url": "https://raw.githubusercontent.com/GitLatte/Sinetech/builds/Müzik TV ve Radyo - LoDi.cs3",
    "name": "Müzik TV ve Radyo - LoDi"
  },
  {
    "iconUrl": "https://raw.githubusercontent.com/GitLatte/temporarylists/refs/heads/main/img/powerdizi.png",
    "apiVersion": 1,
    "repositoryUrl": "https://github.com/GitLatte/Sinetech",
    "fileSize": 34237,
    "status": 1,
    "language": "tr",
    "authors": [
      "lodistream"
    ],
    "tvTypes": [
      "TvSeries"
    ],
    "version": 6,
    "internalName": "powerboard Dizi - LoDi",
    "description": "powerboard`un yabancı dizi arşivi",
    "url": "https://raw.githubusercontent.com/GitLatte/Sinetech/builds/powerboard Dizi - LoDi.cs3",
    "name": "powerboard Dizi - LoDi"
  },
  {
    "iconUrl": "https://raw.githubusercontent.com/GitLatte/temporarylists/refs/heads/main/img/powersinema.png",
    "apiVersion": 1,
    "repositoryUrl": "https://github.com/GitLatte/Sinetech",
    "fileSize": 29254,
    "status": 1,
    "language": "tr",
    "authors": [
      "lodistream"
    ],
    "tvTypes": [
      "Movie"
    ],
    "version": 5,
    "internalName": "powerboard Sinema - LoDi",
    "description": "powerboard`un sinema arşivi",
    "url": "https://raw.githubusercontent.com/GitLatte/Sinetech/builds/powerboard Sinema - LoDi.cs3",
    "name": "powerboard Sinema - LoDi"
  },
  {
    "iconUrl": "https://raw.githubusercontent.com/GitLatte/temporarylists/refs/heads/main/img/bahcesitv.png",
    "apiVersion": 1,
    "repositoryUrl": "https://github.com/GitLatte/Sinetech",
    "fileSize": 20365,
    "status": 1,
    "language": "tr",
    "authors": [
      "lodistream",
    ],
    "tvTypes": [
      "Live"
    ],
    "version": 3,
    "internalName": "Tv Bahçesi - LoDi",
    "description": "TvGarden televizyon listesi. @keyiflerolsun Canlı TV eklentisinden yararlanılmıştır.",
    "url": "https://raw.githubusercontent.com/GitLatte/Sinetech/builds/Tv Bahçesi - LoDi.cs3",
    "name": "Tv Bahçesi - LoDi"
  },
  {
    "iconUrl": "https://webdramaturkey.org/public/static/logo.webp?v=2.1.8",
    "apiVersion": 1,
    "repositoryUrl": "https://github.com/GitLatte/Sinetech",
    "fileSize": 32680,
    "status": 1,
    "language": "tr",
    "authors": [
      "lodistream",
    ],
    "tvTypes": [
      "Movie",
      "Podcast",
      "AsianDrama",
      "Anime"
    ],
    "version": 3,
    "internalName": "WebDramaTurkey - LoDi",
    "description": "Kore, Çin ve Japon yapımı filmleri Web Drama Turkey üzerinden Türkçe altyazılı olarak izleyebilirsiniz. Kore filmi izle, Çin filmi izle, Asya filmleri izle.",
    "url": "https://raw.githubusercontent.com/GitLatte/Sinetech/builds/WebDramaTurkey - LoDi.cs3",
    "name": "WebDramaTurkey - LoDi"
  },
  {
    "iconUrl": "https://raw.githubusercontent.com/GitLatte/temporarylists/refs/heads/main/Latte%20Tube/latte-tube.png",
    "apiVersion": 1,
    "repositoryUrl": "https://github.com/GitLatte/Sinetech",
    "fileSize": 13644,
    "status": 1,
    "language": "tr",
    "authors": [
      "lodistream"
    ],
    "tvTypes": [
      "Live"
    ],
    "version": 1,
    "internalName": "YouTube Özel - LoDi",
    "description": "Youtube 7/24 içeriklerinden derlemeler içerir. Orijinal youtube ile oynatılarak kullanılmaktadır. Bu konuda @feroxx`un geliştirdiği youtube extractor için teşekkürler.",
    "url": "https://raw.githubusercontent.com/GitLatte/Sinetech/builds/YouTube Özel - LoDi.cs3",
    "name": "YouTube Özel - LoDi"
  }
]
